cwl_subworkflows/__init__.py
cwl_subworkflows/cwl_subworkflows.py
cwl_subworkflows-0.1.0.dist-info/AUTHORS.rst
cwl_subworkflows-0.1.0.dist-info/LICENSE
cwl_subworkflows-0.1.0.dist-info/METADATA
cwl_subworkflows-0.1.0.dist-info/WHEEL
cwl_subworkflows-0.1.0.dist-info/top_level.txt
cwl_subworkflows-0.1.0.dist-info/RECORD
