Metadata-Version: 2.1
Name: cwl-subworkflows
Version: 0.1.0
Summary: A list of subworkflows used for MSK-ACCESS data processing.
Home-page: https://github.com/rhshah/cwl_subworkflows
Author: Ronak Shah
Author-email: rons.shah@gmail.com
License: Apache Software License 2.0
Keywords: cwl_subworkflows
Platform: UNKNOWN
Classifier: Development Status :: 2 - Pre-Alpha
Classifier: Intended Audience :: Developers
Classifier: License :: OSI Approved :: Apache Software License
Classifier: Natural Language :: English
Classifier: Programming Language :: Python :: 3.7
